font2img.py
font2img-2.2.dist-info/LICENSE
font2img-2.2.dist-info/METADATA
font2img-2.2.dist-info/WHEEL
font2img-2.2.dist-info/top_level.txt
font2img-2.2.dist-info/RECORD
