Metadata-Version: 2.1
Name: font2img
Version: 2.2
Summary: Drawing glyph in font file (woff, tff ..) 
Home-page: UNKNOWN
Author: coderfly,magicalbomb
Author-email: coderflying@163.com,3379747207@qq.com
License: MIT
Platform: UNKNOWN
Classifier: Programming Language :: Python :: 3
Classifier: License :: OSI Approved :: MIT License
Classifier: Operating System :: OS Independent
Requires-Python: >=3.5
Requires-Dist: pillow
Requires-Dist: fonttools
Requires-Dist: reportlab
